{
    "/js/app.js": "/js/app.js",
    "/js/manifest.js": "/js/manifest.js",
    "/js/chunks/visitors.js": "/js/chunks/visitors.js?id=e72b30063c2263ebd2e6",
    "/js/chunks/accounting.js": "/js/chunks/accounting.js?id=e0e08f75359b4443e113",
    "/js/chunks/fundraising.js": "/js/chunks/fundraising.js?id=dd4aa8444877574ebdf6",
    "/js/chunks/reports.js": "/js/chunks/reports.js?id=9d4090d07f7bef4755cc",
    "/js/chunks/user-management.js": "/js/chunks/user-management.js?id=a58079dc775921b30327",
    "/js/chunks/cmtyvol.js": "/js/chunks/cmtyvol.js?id=b1aad3b8f475a509923b",
    "/css/app.css": "/css/app.css",
    "/js/vendor.js": "/js/vendor.js",
    "/webfonts/fa-brands-400.eot": "/webfonts/fa-brands-400.eot",
    "/webfonts/fa-brands-400.svg": "/webfonts/fa-brands-400.svg",
    "/webfonts/fa-brands-400.ttf": "/webfonts/fa-brands-400.ttf",
    "/webfonts/fa-brands-400.woff": "/webfonts/fa-brands-400.woff",
    "/webfonts/fa-brands-400.woff2": "/webfonts/fa-brands-400.woff2",
    "/webfonts/fa-regular-400.eot": "/webfonts/fa-regular-400.eot",
    "/webfonts/fa-regular-400.svg": "/webfonts/fa-regular-400.svg",
    "/webfonts/fa-regular-400.ttf": "/webfonts/fa-regular-400.ttf",
    "/webfonts/fa-regular-400.woff": "/webfonts/fa-regular-400.woff",
    "/webfonts/fa-regular-400.woff2": "/webfonts/fa-regular-400.woff2",
    "/webfonts/fa-solid-900.eot": "/webfonts/fa-solid-900.eot",
    "/webfonts/fa-solid-900.svg": "/webfonts/fa-solid-900.svg",
    "/webfonts/fa-solid-900.ttf": "/webfonts/fa-solid-900.ttf",
    "/webfonts/fa-solid-900.woff": "/webfonts/fa-solid-900.woff",
    "/webfonts/fa-solid-900.woff2": "/webfonts/fa-solid-900.woff2",
    "/css/font/summernote.eot": "/css/font/summernote.eot",
    "/css/font/summernote.ttf": "/css/font/summernote.ttf",
    "/css/font/summernote.woff": "/css/font/summernote.woff",
    "/css/font/summernote.woff2": "/css/font/summernote.woff2"
}
